{
  "schemaVersion": 1,
  "source": "design/10-lists/ITEM_LIST.md",
  "generatedBy": "design/10-lists/data/build_data_json.py",
  "count": 115,
  "items": [
    {
      "id": "itm_001",
      "category": "回復",
      "name": "おむすび",
      "effect": "HP小回復（単体・即時）",
      "source": "里の店・道中",
      "max": "9",
      "note": "序盤の常備食。体験版から登場"
    },
    {
      "id": "itm_002",
      "category": "回復",
      "name": "焼きむすび",
      "effect": "HP中回復（単体）",
      "source": "店・宝箱",
      "max": "9",
      "note": "香ばしい中量回復"
    },
    {
      "id": "itm_003",
      "category": "回復",
      "name": "重ね握り",
      "effect": "HP大回復（単体）",
      "source": "店（中盤〜）",
      "max": "5",
      "note": "まとめ食い向き"
    },
    {
      "id": "itm_004",
      "category": "回復",
      "name": "椿餅",
      "effect": "HP全快（単体・希少）",
      "source": "隠し・特産交換",
      "max": "3",
      "note": "高価。ここぞの全快"
    },
    {
      "id": "itm_005",
      "category": "回復",
      "name": "串団子",
      "effect": "HP小回復＋歩行中もゆっくり継続回復（数秒）",
      "source": "茶屋",
      "max": "5",
      "note": "変: 歩きながら回復が続く"
    },
    {
      "id": "itm_006",
      "category": "回復",
      "name": "甘酒",
      "effect": "MP小回復",
      "source": "里の店",
      "max": "9",
      "note": "Systems §5 既出"
    },
    {
      "id": "itm_007",
      "category": "回復",
      "name": "濃茶",
      "effect": "MP中回復",
      "source": "店・宿",
      "max": "9",
      "note": ""
    },
    {
      "id": "itm_008",
      "category": "回復",
      "name": "神饌酒（みき）",
      "effect": "MP大回復",
      "source": "社・特産交換",
      "max": "5",
      "note": "神事の御神酒"
    },
    {
      "id": "itm_009",
      "category": "回復",
      "name": "五色団子",
      "effect": "HP・MP同時に小回復",
      "source": "祭事・店",
      "max": "5",
      "note": "両刀の常用品"
    },
    {
      "id": "itm_010",
      "category": "回復",
      "name": "力餅",
      "effect": "HP中回復＋短時間 最大HPを上げ底",
      "source": "山の茶屋",
      "max": "3",
      "note": "変: 一時的に器を増やす"
    },
    {
      "id": "itm_011",
      "category": "回復",
      "name": "蜜柑（みかん）",
      "effect": "HP小回復。連続で食べるほど回復量が逓増（3個目まで）",
      "source": "多島海・果樹",
      "max": "9",
      "note": "変: 連食ボーナス"
    },
    {
      "id": "itm_012",
      "category": "回復",
      "name": "七草粥",
      "effect": "HP中回復＋全状態異常を弱く緩和",
      "source": "宿・年中行事",
      "max": "3",
      "note": "回復×お清めのハイブリッド"
    },
    {
      "id": "itm_013",
      "category": "お清め",
      "name": "清めの塩",
      "effect": "自身周囲の範囲デバフ・穢れを解除",
      "source": "店・社",
      "max": "9",
      "note": "Systems §5 既出。世界観と実用の一致"
    },
    {
      "id": "itm_014",
      "category": "お清め",
      "name": "炒り豆",
      "effect": "投擲。鬼系に特効×2／命中で短時間ひるみ",
      "source": "店・節分行事",
      "max": "9",
      "note": "Systems §5 既出。投擲消費型"
    },
    {
      "id": "itm_015",
      "category": "お清め",
      "name": "禊（みそぎ）の水",
      "effect": "全状態異常を一括解除（高級）",
      "source": "社・特産交換",
      "max": "3",
      "note": "万能解除。希少"
    },
    {
      "id": "itm_016",
      "category": "お清め",
      "name": "解毒の薬湯",
      "effect": "毒を治療",
      "source": "店・薬師",
      "max": "9",
      "note": ""
    },
    {
      "id": "itm_017",
      "category": "お清め",
      "name": "鎮め草",
      "effect": "火点き（燃焼）を消火・治療",
      "source": "道中採取",
      "max": "9",
      "note": ""
    },
    {
      "id": "itm_018",
      "category": "お清め",
      "name": "解（ほど）きの紙垂",
      "effect": "縛り（麻痺）を解除",
      "source": "店・社",
      "max": "9",
      "note": "結び師らしい解除具"
    },
    {
      "id": "itm_019",
      "category": "お清め",
      "name": "目明かしの雫",
      "effect": "眩み（暗闇）を解除",
      "source": "店",
      "max": "9",
      "note": ""
    },
    {
      "id": "itm_020",
      "category": "お清め",
      "name": "活力の生姜湯",
      "effect": "鈍足を解除＋短時間 鈍足耐性",
      "source": "宿・茶屋",
      "max": "5",
      "note": "治療＋予防の二段"
    },
    {
      "id": "itm_021",
      "category": "お清め",
      "name": "祓いの御幣（ごへい）",
      "effect": "呪いを解除",
      "source": "社・神職NPC",
      "max": "5",
      "note": ""
    },
    {
      "id": "itm_022",
      "category": "お清め",
      "name": "鎮心香（ちんしんこう）",
      "effect": "混乱を解除",
      "source": "店",
      "max": "9",
      "note": ""
    },
    {
      "id": "itm_023",
      "category": "お清め",
      "name": "榊（さかき）の小枝",
      "effect": "一定時間 穢れの付与を無効化（予防）",
      "source": "社・採取",
      "max": "5",
      "note": "変: 治療でなく予防型"
    },
    {
      "id": "itm_024",
      "category": "お清め",
      "name": "塩むすび",
      "effect": "HP小回復＋周囲の範囲デバフ解除",
      "source": "店・道中",
      "max": "9",
      "note": "回復×お清めの携行品"
    },
    {
      "id": "itm_025",
      "category": "復活",
      "name": "起き上がりだるま",
      "effect": "所持中、戦闘不能時に自動復活（HP25%）・1回限り",
      "source": "店（高価）・宝箱",
      "max": "3",
      "note": "Systems §5 既出。高価・希少"
    },
    {
      "id": "itm_026",
      "category": "復活",
      "name": "七転（ななころ）の福だるま",
      "effect": "自動復活（HP60%）＋復活後 短時間無敵",
      "source": "終盤店・隠し",
      "max": "2",
      "note": "だるま上位。希少"
    },
    {
      "id": "itm_027",
      "category": "復活",
      "name": "みたま返しの札",
      "effect": "戦闘不能の瞬間に手動使用でHP全回復し踏みとどまる",
      "source": "符師・特産交換",
      "max": "3",
      "note": "変: 手動発動の保険"
    },
    {
      "id": "itm_028",
      "category": "復活",
      "name": "黄泉戸喫（よもつへぐい）封じの米",
      "effect": "常世/高天原の即死級ギミックを1回無効化",
      "source": "R8/R10 限定",
      "max": "3",
      "note": "終盤・テーマ品。希少"
    },
    {
      "id": "itm_029",
      "category": "バフ",
      "name": "力の丸薬",
      "effect": "一定時間 攻撃力+20%",
      "source": "店・薬師",
      "max": "9",
      "note": "攻バフ基礎"
    },
    {
      "id": "itm_030",
      "category": "バフ",
      "name": "守りの丸薬",
      "effect": "一定時間 被ダメージ-20%",
      "source": "店・薬師",
      "max": "9",
      "note": "守バフ基礎"
    },
    {
      "id": "itm_031",
      "category": "バフ",
      "name": "疾風の丸薬",
      "effect": "一定時間 移動・攻撃速度+15%",
      "source": "店",
      "max": "9",
      "note": "速バフ基礎"
    },
    {
      "id": "itm_032",
      "category": "バフ",
      "name": "祓いの神酒",
      "effect": "一定時間 祓いゲージ蓄積+50%",
      "source": "社・特産交換",
      "max": "5",
      "note": "祓い波回し"
    },
    {
      "id": "itm_033",
      "category": "バフ",
      "name": "会心の香",
      "effect": "一定時間 会心率+15%",
      "source": "店（中盤〜）",
      "max": "5",
      "note": "単体火力寄り"
    },
    {
      "id": "itm_034",
      "category": "バフ",
      "name": "不動の香",
      "effect": "一定時間 のけぞり/スタンを無効化",
      "source": "店・鍛冶",
      "max": "5",
      "note": "崩され対策"
    },
    {
      "id": "itm_035",
      "category": "バフ",
      "name": "鬼斬の札",
      "effect": "一定時間 鬼系への特効+30%",
      "source": "符師・社",
      "max": "5",
      "note": "対象限定バフ"
    },
    {
      "id": "itm_036",
      "category": "バフ",
      "name": "韋駄天の足袋（消費札）",
      "effect": "一定時間 ダッシュ硬直なし・回避距離増",
      "source": "店・隠し",
      "max": "5",
      "note": "機動特化"
    },
    {
      "id": "itm_037",
      "category": "バフ",
      "name": "金運の小判",
      "effect": "一定時間 敵が落とす銭+50%",
      "source": "縁日・隠し",
      "max": "3",
      "note": "変: 稼ぎ系バフ"
    },
    {
      "id": "itm_038",
      "category": "バフ",
      "name": "慧眼の香",
      "effect": "一定時間 敵の弱点（武器相性）を可視化",
      "source": "薬師・収集報酬",
      "max": "3",
      "note": "変: 相性が見える"
    },
    {
      "id": "itm_039",
      "category": "バフ",
      "name": "倍返しの護符",
      "effect": "一定時間 被弾時に反射ダメージ",
      "source": "符師（終盤）",
      "max": "3",
      "note": "変: カウンター型"
    },
    {
      "id": "itm_040",
      "category": "バフ",
      "name": "静寂の香",
      "effect": "一定時間 敵の感知範囲を縮小",
      "source": "店・式符師",
      "max": "5",
      "note": "変: スニーク補助"
    },
    {
      "id": "itm_041",
      "category": "探索",
      "name": "提灯",
      "effect": "暗所の視界確保（携行）",
      "source": "里の店（体験版から購入可）",
      "max": "1",
      "note": "Systems §5 既出。暗所の鍵化防止の要"
    },
    {
      "id": "itm_042",
      "category": "探索",
      "name": "強火の提灯",
      "effect": "暗所視界が広い上位提灯",
      "source": "店（中盤〜）・宝箱",
      "max": "1",
      "note": "提灯の快適版"
    },
    {
      "id": "itm_043",
      "category": "探索",
      "name": "松明",
      "effect": "暗所視界＋周囲の枯草・蔦に着火（探索ギミック）",
      "source": "店・道中",
      "max": "9",
      "note": "消費型。火付けの任意ギミック"
    },
    {
      "id": "itm_044",
      "category": "探索",
      "name": "縄（なわ）",
      "effect": "段差・対岸に一度だけ足場を作る",
      "source": "店・宝箱",
      "max": "9",
      "note": "任意ルート短縮"
    },
    {
      "id": "itm_045",
      "category": "探索",
      "name": "鉤縄（かぎなわ）",
      "effect": "高所の宝箱・ショートカットに引っ掛ける",
      "source": "宝箱・隠し",
      "max": "5",
      "note": "任意の寄り道用"
    },
    {
      "id": "itm_046",
      "category": "探索",
      "name": "桐箱の鍵",
      "effect": "一般宝箱（必須経路でない）を開ける汎用鍵",
      "source": "店・ドロップ",
      "max": "9",
      "note": "消費型・宝箱専用"
    },
    {
      "id": "itm_047",
      "category": "探索",
      "name": "錆びた鍵",
      "effect": "古い社・蔵の宝箱を開ける",
      "source": "地域限定ドロップ",
      "max": "5",
      "note": "地域限定の宝向け"
    },
    {
      "id": "itm_048",
      "category": "探索",
      "name": "帰りの紙鳥（かみどり）",
      "effect": "直近の拠点へ即時帰還",
      "source": "店・社",
      "max": "5",
      "note": "消費ワープ（任意の利便）"
    },
    {
      "id": "itm_049",
      "category": "探索",
      "name": "道しるべの鈴",
      "effect": "一定時間 未探索の宝/祠をマップに点滅表示",
      "source": "収集報酬・店",
      "max": "3",
      "note": "変: 探索快適化"
    },
    {
      "id": "itm_050",
      "category": "探索",
      "name": "潮見の貝笛",
      "effect": "干潮/満潮を任意で1回早送り",
      "source": "多島海・常世（R2/R8）",
      "max": "5",
      "note": "潮ギミックの近道（必須でない）"
    },
    {
      "id": "itm_051",
      "category": "収集",
      "name": "手控え帳・里山の段",
      "effect": "R1 のページを集める",
      "source": "R1 探索",
      "max": "1",
      "note": "8段揃いで恒久報酬"
    },
    {
      "id": "itm_052",
      "category": "収集",
      "name": "手控え帳・多島海の段",
      "effect": "R2 のページ",
      "source": "R2 探索",
      "max": "1",
      "note": ""
    },
    {
      "id": "itm_053",
      "category": "収集",
      "name": "手控え帳・宮乃京の段",
      "effect": "R3 のページ",
      "source": "R3 探索",
      "max": "1",
      "note": ""
    },
    {
      "id": "itm_054",
      "category": "収集",
      "name": "手控え帳・霊峰の段",
      "effect": "R4 のページ",
      "source": "R4 探索",
      "max": "1",
      "note": ""
    },
    {
      "id": "itm_055",
      "category": "収集",
      "name": "手控え帳・北雪の段",
      "effect": "R5 のページ",
      "source": "R5 探索",
      "max": "1",
      "note": ""
    },
    {
      "id": "itm_056",
      "category": "収集",
      "name": "手控え帳・幽谷の段",
      "effect": "R6 のページ",
      "source": "R6 探索",
      "max": "1",
      "note": ""
    },
    {
      "id": "itm_057",
      "category": "収集",
      "name": "手控え帳・常世の段",
      "effect": "R8 のページ",
      "source": "R8 探索",
      "max": "1",
      "note": ""
    },
    {
      "id": "itm_058",
      "category": "収集",
      "name": "手控え帳・高天原の段",
      "effect": "R10 のページ",
      "source": "R10 探索",
      "max": "1",
      "note": "全8段で勾玉枠+1 等の恒久報酬"
    },
    {
      "id": "itm_059",
      "category": "収集",
      "name": "妖の図譜（あやかしのずふ）",
      "effect": "敵を倒すと埋まる図鑑",
      "source": "戦闘で自動",
      "max": "1",
      "note": "完成で対妖ダメ恒久＋"
    },
    {
      "id": "itm_060",
      "category": "収集",
      "name": "名所の拓本帖",
      "effect": "景観ポイントで拓本を取る",
      "source": "名所で採取",
      "max": "1",
      "note": "完成で移動速度恒久＋"
    },
    {
      "id": "itm_061",
      "category": "収集",
      "name": "釣り手帖",
      "effect": "釣った魚を記録",
      "source": "釣り場",
      "max": "1",
      "note": "完成で回復食レシピ解放"
    },
    {
      "id": "itm_062",
      "category": "収集",
      "name": "結びの口伝書",
      "effect": "各地の祠で歌片を集める",
      "source": "祠（依代）",
      "max": "1",
      "note": "全収集で隠しスキル/真エンド条件の一部"
    },
    {
      "id": "itm_063",
      "category": "地域特産",
      "name": "山鉄（やまがね）",
      "effect": "売却＝銭／武器強化（基礎）",
      "source": "R1 satoyama",
      "max": "99",
      "note": "W1〜W8 序盤強化の基礎材"
    },
    {
      "id": "itm_064",
      "category": "地域特産",
      "name": "青竹",
      "effect": "売却＝銭／武器強化・クラフト",
      "source": "R1 satoyama",
      "max": "99",
      "note": "弓・薙刀・縄の素材"
    },
    {
      "id": "itm_065",
      "category": "地域特産",
      "name": "珊瑚（真珠とも）",
      "effect": "売却＝銭／武器強化（海素材）",
      "source": "R2 tatoukai",
      "max": "99",
      "note": "刀g4・鏡g4・弓g4・薙刀g4 等"
    },
    {
      "id": "itm_066",
      "category": "地域特産",
      "name": "潮塩（藻塩とも）",
      "effect": "売却＝銭／武器強化（海素材）",
      "source": "R2 tatoukai",
      "max": "99",
      "note": "槌・薙刀・式符・錫杖の強化"
    },
    {
      "id": "itm_067",
      "category": "地域特産",
      "name": "金箔",
      "effect": "売却＝銭（高）／武器強化（都の工芸）",
      "source": "R3 miyanokyo",
      "max": "99",
      "note": "刀g5・鏡g5・弓・舞扇 等"
    },
    {
      "id": "itm_068",
      "category": "地域特産",
      "name": "漆（うるし）",
      "effect": "売却＝銭／武器強化（都の工芸）",
      "source": "R3 miyanokyo",
      "max": "99",
      "note": "槌g5・鏡g3・式符・錫杖 等"
    },
    {
      "id": "itm_069",
      "category": "地域特産",
      "name": "火打石",
      "effect": "売却＝銭／武器強化（火付与）",
      "source": "R4 reihou",
      "max": "99",
      "note": "多系統の火付与強化"
    },
    {
      "id": "itm_070",
      "category": "地域特産",
      "name": "霊砂（れいさ）",
      "effect": "売却＝銭／武器強化（霊力）",
      "source": "R4 reihou",
      "max": "99",
      "note": "鏡g6 眩み等の霊力強化"
    },
    {
      "id": "itm_071",
      "category": "地域特産",
      "name": "氷晶",
      "effect": "売却＝銭／武器強化（冷気付与）",
      "source": "R5 hokusetsu",
      "max": "99",
      "note": "刀g7・鏡g7・弓g7・式符g7 等"
    },
    {
      "id": "itm_072",
      "category": "地域特産",
      "name": "白銀（しろがね）",
      "effect": "売却＝銭（高）／武器強化",
      "source": "R5 hokusetsu",
      "max": "99",
      "note": "薙刀g7・舞扇g7 等"
    },
    {
      "id": "itm_073",
      "category": "地域特産",
      "name": "黒杉",
      "effect": "売却＝銭／武器強化（暗所素材）",
      "source": "R6 kurosu",
      "max": "99",
      "note": "刀g8・槌g8・薙刀g8・弓g8 等"
    },
    {
      "id": "itm_074",
      "category": "地域特産",
      "name": "夜光苔（やこうごけ）",
      "effect": "売却＝銭／武器強化（暗所素材）",
      "source": "R6 kurosu",
      "max": "99",
      "note": "鏡g8・式符g8・舞扇g8・錫杖g8 等"
    },
    {
      "id": "itm_075",
      "category": "地域特産",
      "name": "常世貝（とこよがい）",
      "effect": "売却＝銭（高）／武器強化",
      "source": "R8 tokoyo",
      "max": "99",
      "note": "刀g9・鏡g9・薙刀g9・式符g9・錫杖g9 等"
    },
    {
      "id": "itm_076",
      "category": "地域特産",
      "name": "潮玉（しおだま）",
      "effect": "売却＝銭（高）／武器強化",
      "source": "R8 tokoyo",
      "max": "99",
      "note": "槌g9・弓g9・舞扇g9 等"
    },
    {
      "id": "itm_077",
      "category": "地域特産",
      "name": "神鉄（かむがね）",
      "effect": "売却＝銭（最高）／武器最終強化（g10・希少）",
      "source": "R10 takamagahara",
      "max": "99",
      "note": "刀/槌/薙刀/弓/式符 の g10"
    },
    {
      "id": "itm_078",
      "category": "地域特産",
      "name": "天羽根（あまのはね）",
      "effect": "売却＝銭（最高）／武器最終強化（g10・希少）",
      "source": "R10 takamagahara",
      "max": "99",
      "note": "鏡/舞扇 の g10・錫杖最終"
    },
    {
      "id": "itm_079",
      "category": "クラフト素材",
      "name": "木の枝",
      "effect": "クラフト基礎材（縄・松明等）",
      "source": "道中採取",
      "max": "99",
      "note": "汎用"
    },
    {
      "id": "itm_080",
      "category": "クラフト素材",
      "name": "丈夫な蔓（つる）",
      "effect": "クラフト材（縄・鉤縄）",
      "source": "採取",
      "max": "99",
      "note": ""
    },
    {
      "id": "itm_081",
      "category": "クラフト素材",
      "name": "なめし革",
      "effect": "クラフト材（衣の補修・足袋）",
      "source": "店・ドロップ",
      "max": "99",
      "note": ""
    },
    {
      "id": "itm_082",
      "category": "クラフト素材",
      "name": "砥石（といし）",
      "effect": "武器の手入れ（強化補助・微強化素材）",
      "source": "店・採取",
      "max": "99",
      "note": ""
    },
    {
      "id": "itm_083",
      "category": "クラフト素材",
      "name": "薬草",
      "effect": "回復食・薬湯の素",
      "source": "採取",
      "max": "99",
      "note": ""
    },
    {
      "id": "itm_084",
      "category": "クラフト素材",
      "name": "毒消し草",
      "effect": "解毒の薬湯の素",
      "source": "採取",
      "max": "99",
      "note": ""
    },
    {
      "id": "itm_085",
      "category": "クラフト素材",
      "name": "鬼の角",
      "effect": "バフ札・鬼斬の札の素（鬼系ドロップ）",
      "source": "鬼系ドロップ",
      "max": "99",
      "note": ""
    },
    {
      "id": "itm_086",
      "category": "クラフト素材",
      "name": "妖（あやかし）の羽",
      "effect": "バフ香・舞扇強化補助の素",
      "source": "飛行妖ドロップ",
      "max": "99",
      "note": ""
    },
    {
      "id": "itm_087",
      "category": "クラフト素材",
      "name": "粘つく糸",
      "effect": "トラップ・式符補助の素",
      "source": "蜘蛛系ドロップ",
      "max": "99",
      "note": ""
    },
    {
      "id": "itm_088",
      "category": "クラフト素材",
      "name": "火の素（燃石）",
      "effect": "松明・火付与系の素",
      "source": "霊峰採取",
      "max": "99",
      "note": ""
    },
    {
      "id": "itm_089",
      "category": "クラフト素材",
      "name": "清水（霊験ある湧水）",
      "effect": "禊の水・上位回復の素",
      "source": "社・湧水",
      "max": "99",
      "note": ""
    },
    {
      "id": "itm_090",
      "category": "クラフト素材",
      "name": "和紙",
      "effect": "式符・手控え帳・御幣の素",
      "source": "店・採取",
      "max": "99",
      "note": ""
    },
    {
      "id": "itm_091",
      "category": "クラフト素材",
      "name": "墨（すみ）",
      "effect": "式符の素（符師クラフト）",
      "source": "店・宮乃京",
      "max": "99",
      "note": "W6 式符の作製材"
    },
    {
      "id": "itm_092",
      "category": "クラフト素材",
      "name": "麻糸（あさいと）",
      "effect": "結び・縄・紙垂の素",
      "source": "店・採取",
      "max": "99",
      "note": "結び師の基礎材"
    },
    {
      "id": "itm_093",
      "category": "イベントキー",
      "name": "結びの勾玉（片割れ）",
      "effect": "主人公の形見。物語の起点・全編の鍵",
      "source": "プロローグ",
      "max": "1",
      "note": "終盤で対となる片割れと結ばれる"
    },
    {
      "id": "itm_094",
      "category": "イベントキー",
      "name": "里長の書状",
      "effect": "R1→R2/R3 への紹介状（関所通過）",
      "source": "R1 メイン",
      "max": "1",
      "note": "序盤の地域解放トリガー"
    },
    {
      "id": "itm_095",
      "category": "イベントキー",
      "name": "渡し守の割符",
      "effect": "R2 多島海の船の通行手形",
      "source": "R2 メイン",
      "max": "1",
      "note": "船移動の解放"
    },
    {
      "id": "itm_096",
      "category": "イベントキー",
      "name": "帝（みかど）の勅許状",
      "effect": "R3 宮乃京 中枢への入場許可",
      "source": "R3 メイン",
      "max": "1",
      "note": "中央ハブ深部の解放"
    },
    {
      "id": "itm_097",
      "category": "イベントキー",
      "name": "霊峰の登拝札（とはいふだ）",
      "effect": "R4 霊峰の入山許可",
      "source": "R4 メイン",
      "max": "1",
      "note": "縦地形ダンジョンの解放"
    },
    {
      "id": "itm_098",
      "category": "イベントキー",
      "name": "雪解けの鈴",
      "effect": "R5 凍結した社を開く儀式具",
      "source": "R5 メイン",
      "max": "1",
      "note": "雪郷の封印解除"
    },
    {
      "id": "itm_099",
      "category": "イベントキー",
      "name": "常世への渡り符",
      "effect": "R8 常世の浜へ渡る",
      "source": "R8 メイン",
      "max": "1",
      "note": "外洋・常世への進行"
    },
    {
      "id": "itm_100",
      "category": "イベントキー",
      "name": "天逆鉾（あまのさかほこ）の欠片",
      "effect": "R10 高天原・最終封印に関わる神宝",
      "source": "R10 メイン",
      "max": "1",
      "note": "終局イベントの鍵"
    },
    {
      "id": "itm_101",
      "category": "回復",
      "name": "湯治の湯（ゆじのゆ）",
      "effect": "HP中回復＋数秒HP継続回復",
      "source": "R7 湯ノ鬼郷（回復湯ノ社）・店",
      "max": "5",
      "note": "温泉郷の携行湯。変: 歩行中も回復継続"
    },
    {
      "id": "itm_102",
      "category": "回復",
      "name": "蓮の実粥（はすのみがゆ）",
      "effect": "HP・MP同時に小回復",
      "source": "R8 澪渡りの湿地（採取・無戦闘）",
      "max": "5",
      "note": "常世の精進食。探索消耗の癒し"
    },
    {
      "id": "itm_103",
      "category": "バフ",
      "name": "湯治の効能（とうじのこうのう）",
      "effect": "一定時間 最大HP上げ底＋被ダメ −10%（重複不可）",
      "source": "R7 湯ノ鬼郷（湯守）・特産交換",
      "max": "5",
      "note": "温泉浴の複合バフ。火の地方の戦闘準備"
    },
    {
      "id": "itm_104",
      "category": "探索",
      "name": "火種（ひだね）",
      "effect": "松明・かがり火・封じの篝に着火し火山地形の暗所を一時可視化",
      "source": "R7 噴気の谷・鍛冶の街（消費型）",
      "max": "9",
      "note": "鍵化しない快適枠（§0.1-2）。火付け任意ギミック"
    },
    {
      "id": "itm_105",
      "category": "収集",
      "name": "常世の記憶片（とこよのきおくへん）",
      "effect": "常世の巫が宿す記憶。集めると恒久報酬",
      "source": "R8 澪渡りの湿地・常世の大社（依代点灯/記憶儀式・無戦闘）",
      "max": "1",
      "note": "全集めで常世の勾玉 mag_011 に関わる恒久報酬"
    },
    {
      "id": "itm_106",
      "category": "収集",
      "name": "星図の欠片（せいずのかけら）",
      "effect": "夜空の星位で集める。星座完成で恒久報酬",
      "source": "R10 常闇と星空（夜間採取）",
      "max": "1",
      "note": "完成で夜間視界/移動の恒久＋"
    },
    {
      "id": "itm_107",
      "category": "地域特産",
      "name": "たたら鉄（たたらがね）",
      "effect": "売却＝銭／武器強化（火属性上位段階の中核材）",
      "source": "R7 鍛冶の街たたら（boss_17 鉄喰いの大鬼 も特上ドロップ）",
      "max": "99",
      "note": "9地域×2 の R7特産①。火属性 g6〜の代替強化材"
    },
    {
      "id": "itm_108",
      "category": "地域特産",
      "name": "石灰華（せっかいか）",
      "effect": "売却＝銭／武器強化（白磐の研磨材）",
      "source": "R7 白磐の野（カルスト）・enm_067 白岩の蟲",
      "max": "99",
      "note": "9地域×2 の R7特産②。砥石系の上位研磨"
    },
    {
      "id": "itm_109",
      "category": "クラフト素材",
      "name": "火山砂（かざんずな）",
      "effect": "火付与・符のクラフト素材",
      "source": "R7 噴気の谷・地獄谷 採取",
      "max": "99",
      "note": "火の素 itm_088 の上位互換素材"
    },
    {
      "id": "itm_110",
      "category": "クラフト素材",
      "name": "鍾乳石（しょうにゅうせき）",
      "effect": "砥石上位・防具補修のクラフト素材",
      "source": "R7 鍾乳洞・enm_067 白岩の蟲",
      "max": "99",
      "note": "白磐クラスタの地下素材"
    },
    {
      "id": "itm_111",
      "category": "クラフト素材",
      "name": "硫黄華（いおうばな）",
      "effect": "解毒・火付与のクラフト素材",
      "source": "R7 噴気の谷・地獄谷・enm_066 硫泉の蛭",
      "max": "99",
      "note": "毒消し草 itm_084 と合わせ解毒薬の素"
    },
    {
      "id": "itm_112",
      "category": "クラフト素材",
      "name": "砂金（さきん）",
      "effect": "換金（高）・装飾クラフト素材",
      "source": "R2 鳴り砂の岬（砂丘採取）・enm_063 砂塵の大蜘蛛",
      "max": "99",
      "note": "砂丘サブゾーンの寄り道レア素材"
    },
    {
      "id": "itm_113",
      "category": "クラフト素材",
      "name": "星屑の砂（ほしくずのすな）",
      "effect": "鏡・舞扇の補助クラフト素材",
      "source": "R10 常闇と星空・架け橋・enm_069 星屑の妖",
      "max": "99",
      "note": "高天原の光属性素材"
    },
    {
      "id": "itm_114",
      "category": "クラフト素材",
      "name": "白金砂（はっきんしゃ）",
      "effect": "高位クラフト素材（武具補修・装飾）",
      "source": "R10 雲海・架け橋・enm_071 雲の番人",
      "max": "99",
      "note": "浮島の希少素材"
    },
    {
      "id": "itm_115",
      "category": "クラフト素材",
      "name": "天之羽衣の糸（あまのはごろものいと）",
      "effect": "天羽衣・舞扇系の高位クラフト素材",
      "source": "R10 八雲の架け橋・enm_072 天狗・boss_19 上質ドロップ",
      "max": "99",
      "note": "koromo_11 天羽衣 の補修にも使う最上素材"
    }
  ]
}
